odoo/addons/website_sale_wishlist_archive_cron/README.rst
odoo/addons/website_sale_wishlist_archive_cron/__init__.py
odoo/addons/website_sale_wishlist_archive_cron/__manifest__.py
odoo/addons/website_sale_wishlist_archive_cron/data/cron_data.xml
odoo/addons/website_sale_wishlist_archive_cron/i18n/es.po
odoo/addons/website_sale_wishlist_archive_cron/i18n/website_sale_wishlist_archive_cron.pot
odoo/addons/website_sale_wishlist_archive_cron/models/__init__.py
odoo/addons/website_sale_wishlist_archive_cron/models/product_wishlist.py
odoo/addons/website_sale_wishlist_archive_cron/readme/DESCRIPTION.rst
odoo/addons/website_sale_wishlist_archive_cron/static/description/icon.png
odoo/addons/website_sale_wishlist_archive_cron/static/description/index.html
odoo_addon_website_sale_wishlist_archive_cron-15.0.1.0.0.6.dist-info/METADATA
odoo_addon_website_sale_wishlist_archive_cron-15.0.1.0.0.6.dist-info/WHEEL
odoo_addon_website_sale_wishlist_archive_cron-15.0.1.0.0.6.dist-info/top_level.txt
odoo_addon_website_sale_wishlist_archive_cron-15.0.1.0.0.6.dist-info/RECORD
